setup.cfg
setup.py
hfgp/__init__.py
hfgp/download.py
hfgp/hf_gp.py
hfgp/model.py
hfgp.egg-info/PKG-INFO
hfgp.egg-info/SOURCES.txt
hfgp.egg-info/dependency_links.txt
hfgp.egg-info/requires.txt
hfgp.egg-info/top_level.txt
hfgp/base/__init__.py
hfgp/base/cls_model_op.py
hfgp/base/hf_operator.py
hfgp/base/pipeline.py
hfgp/conf/__init__.py
hfgp/conf/config.py
hfgp/evaluator/__init__.py
hfgp/evaluator/sentence_transformer_evaluator.py
hfgp/pipeline/__init__.py
hfgp/utils/__init__.py
hfgp/utils/data_utils.py
hfgp/utils/download_utils.py
hfgp/utils/utility.py