Metadata-Version: 1.0
Name: hfgp
Version: 0.1.2
Summary: Huggingface GP 接入模块
Home-page: UNKNOWN
Author: stellahong
Author-email: stellahong@fuzhi.a
License: UNKNOWN
Platform: UNKNOWN
